PWrapper/__init__.py
PWrapper/alliance.py
PWrapper/nation.py
PWrapper-0.0.3.dist-info/LICENSE
PWrapper-0.0.3.dist-info/METADATA
PWrapper-0.0.3.dist-info/WHEEL
PWrapper-0.0.3.dist-info/top_level.txt
PWrapper-0.0.3.dist-info/RECORD
